{
  "annotations": [
    {
      "annotator": "Lars Yencken <lars@yencken.org>",
      "date": "2015-04-12",
      "duration": 20,
      "genders": "mixed",
      "label": "bad",
      "offset": 200,
      "problems": [
        "language or place reference"
      ],
      "speakers": 2
    }
  ],
  "checksum": "8770b2a089a537a6b1c09de6c6556aa6",
  "date": "2015-04-04",
  "language": "cmn",
  "media_urls": [
    "http://feedproxy.google.com/~r/radiomandarin/~3/NydYFbtfyTg/mandarin_150405_402920.mp3",
    "http://mirror.widelanguageindex.org/cmn/cmn-8770b2a089a537a6b1c09de6c6556aa6.mp3"
  ],
  "source_name": "SBS Australia",
  "source_url": "http://feedproxy.google.com/~r/radiomandarin/~3/NydYFbtfyTg/mandarin_150405_402920.mp3",
  "title": "Life Magazine: Report from Sydney"
}