{
  "checksum": "d66632595d1e4bb342743c94815fbba8",
  "date": "2012-09-14",
  "language": "mal",
  "media_urls": [
    "http://www.thehindu.com/multimedia/archive/01209/MalayalamDomesticE_1209200a.mp3"
  ],
  "source_name": "The Hindu: Podcasts in Malayam",
  "source_url": "http://www.thehindu.com/opinion/editorial/article3897681.ece?ref=audio",
  "title": "A fair deal for domestic work [Malayalam: Gaarhika thozhilinte neethisastram]. Editorial, September 14, 2012. Translated by Rasmi Binoy, presented by A Correspondent"
}