{
  "annotations": [
    {
      "annotator": "Lars Yencken <lars@yencken.org>",
      "date": "2015-11-15",
      "duration": 20,
      "genders": "male",
      "label": "bad",
      "offset": 300,
      "problems": [
        "noise"
      ],
      "speakers": 1
    },
    {
      "annotator": "Lars Yencken <lars@yencken.org>",
      "date": "2015-11-15",
      "duration": 20,
      "genders": "male",
      "label": "bad",
      "offset": 140,
      "problems": [
        "noise"
      ],
      "speakers": 1
    }
  ],
  "checksum": "d4fa47fc03131478f6647d41e470c58f",
  "date": "1100-10-09",
  "language": "yue",
  "media_urls": [
    "http://feedproxy.google.com/~r/cantonese/~3/F7Ky1_YkaJo/cantonese_151009_445163.mp3",
    "http://mirror.widelanguageindex.org/yue/yue-d4fa47fc03131478f6647d41e470c58f.mp3"
  ],
  "source_name": "SBS Cantonese",
  "source_url": "http://feedproxy.google.com/~r/cantonese/~3/F7Ky1_YkaJo/cantonese_151009_445163.mp3",
  "title": "Shiny Sunday: Episode 11"
}